{
    "primary_type" : {
        "fits_keyword" : "PATTTYPE",
        "title" : "Primary dither pattern type",
        "description" : "MIRI MRS dither pattern type",
        "type" : "string",
        "enum" : ["2-POINT", "4-POINT", "NONE"],
        "units" : "",
        "example" : "2-POINT",
        "default_value" : "NONE",
        "source" : "Proposal and Planning System (PPS)",
        "sw_source" : "PPS:dms_dithers_view.pattern_type|pps_to_scsb_translation|",
        "calculation" : "",
        "destination" : ["ScienceCommon.patttype"],
        "sql_dtype" : "nvarchar(31)",
        "si" : "MIRI",
        "mode" : "MIR_MRS",
        "level" : "1b",
        "fits_hdu" : "PRIMARY",
        "section" : "Dither",
        "misc" : "pps_to_scsb_translation converts underscores to dashes in values"
    },

    "primary_channel" : {
        "fits_keyword" : "MRSPRCHN",
        "title" : "Optimized MRS channel",
        "description" : " The Medium Resolution Spectroscopy (MRS) channel for which the dither pattern is optimized.",
        "type" : "string",
        "enum" : ["ALL", "CHANNEL1", "CHANNEL2", "CHANNEL3", "CHANNEL4"],
        "units" : "",
        "example" : "CHANNEL1",
        "default_value" : "",
        "special_processing" : "OPTIONAL",
        "source" : "Proposal and Planning System (PPS)",
        "sw_source" : "PPS:dms_templates_view.primary_channel",
        "calculation" : "",
        "destination" : ["MiriScience.mrsprchn"],
        "sql_dtype" : "nvarchar(10)",
        "si" : "MIRI",
        "level" : "1b",
        "mode" : "MIR_MRS",
        "fits_hdu" : "PRIMARY",
        "section" : "Dither",
        "misc" : ""
    },

    "optimized_for" : {
        "fits_keyword" : "DITHOPFR",
        "title" : "Dither pattern optimization for point or extended source",
        "description" : "Identifies the type of science for which the dither is optimized, point source or extended source.",
        "type" : "string",
        "enum" : ["EXTENDED-SOURCE", "POINT-SOURCE", "NONE"],
        "units" : "",
        "example" : "",
        "default_value" : "",
        "special_processing" : "OPTIONAL",
        "source" : "Proposal and Planning System (PPS)",
        "sw_source" : "PPS:dms_dithers_view.optimized_for|underscore_to_hyphen|",
        "calculation" : "",
        "destination" : ["MiriScience.dithopfr"],
        "sql_dtype" : "nvarchar(20)",
        "si" : "MIRI",
        "mode" : "MIR_MRS",
        "level" : "1b",
        "fits_hdu" : "PRIMARY",
        "section" : "Dither",
        "misc" : "underscore_to_hyphen changes underscores to dashes in keyword value"
    },

    "direction" : {
        "fits_keyword" : "DITHDIRC",
        "title" : "Direction of dither pattern offsets",
        "description" : "The user-specified direction of dither pattern offsets, positive or negative.",
        "type" : "string",
        "enum" : ["NEGATIVE", "POSITIVE", "NONE"],
        "units" : "",
        "example" : "POSITIVE",
        "default_value" : "",
        "special_processing" : "OPTIONAL",
        "source" : "Proposal and Planning System (PPS)",
        "sw_source" : "PPS:dms_dithers_view.direction",
        "calculation" : "",
        "destination" : ["MiriScience.dithdirc"],
        "sql_dtype" : "nvarchar(10)",
        "si" : "MIRI",
        "mode" : "MIR_MRS",
        "fits_hdu" : "PRIMARY",
        "level" : "1b",
        "section" : "Dither",
        "misc" : ""
    }
}
